{"yaoNhSPn2oL/qLxsvVAy8g==":"foto%20pessoal-384x576.png","ZZiuyifwb0CB6zjA670C0Q==":"section-1366x608.png","H+EanYRHd1+bxdRb6BzjbQ==":"trreo.jpg","tfLUDoBQaIlrS+MOVRmxYg==":"cobertura.jpg","H5g+x55bOWq53y9mtkGo6w==":"trreo-1.jpg","JoJeI3fkkgS20Ukvl6Z9GA==":"222222222.png","Un41UPZgz5NNMMqptpiyYg==":"fachada-gourmet-1-photo.jpg","9oVfpKbEyg1P7+4jTGQ1dQ==":"fachada-gourmet-2-foto.jpg","ULVEB65SZksyrdUg9Stmzw==":"fachada-gourmet-3-foto.jpg","FCA8auWv6LVkSxNI/4qToQ==":"gourmet-4-foto.jpg","nb/D6NOkUa8z4XTN/CH1UA==":"gourmet-5-foto.jpg","6wkfRtMu504Ept9BMxUGCw==":"gourmet-6-foto.jpg","2Li8UmP0707m6G0GcB8dvg==":"gourmet-7-foto.jpg","6Apd18vXGoLO1jtPSMc3gA==":"sala-cozinha-1-photo.jpg","BYjgOwmWk2bXG3+YdR1emA==":"sala-cozinha-2-foto.jpg","2CWcxf4brJ3tEZ3JDzn8VQ==":"header.png","zkeV/By6bhEneJIL0j9+qQ==":"mid-sextion.png","QIU0sH2zetWqXLWKj+EsMw==":"who.png","Hmjo9Xoh9qi5GjpLo/0eHQ==":"background1-1.jpg","eyGWTMT/hyRWEuICZ4rRug==":"435435.png","fRiYnINae4z3BAsZDK7GZA==":"incorfast-consultor-384x600.png","nid6yKxcmR411ZFsgfl2+w==":"whatsapp-image-2021-01-19-at-16.36.08-700x727.png","OtE9gG3iB8461xpaQFW7mA==":"whatsapp-image-2021-01-19-at-16.36.08-1-700x727.png","4iF893sKLl9PpF8FGAczrw==":"tudo-1366x608.png","6Xiupeu0iNVGOGGSRCKYzA==":"imanesid%C3%A3o-1341x179.png"}